<?xml  version='1.0' encoding='windows-1252' ?>
<UMLProfile profiletype="uml2">
	<Documentation id="BAA1A7F3-4" name="mtt-cpp" version="1.1" notes="mtt-cpp"/>
	<Content>
		<Stereotypes>
			<Stereotype name="Application" notes="" cx="0" cy="0" bgcolor="-1" fontcolor="-1" bordercolor="-1" borderwidth="-1" hideicon="0" generalizes="PackageBase" baseStereotypes="PackageBase">
				<AppliesTo>
					<Apply type="Package">
						<Property name="URI" value=""/>
					</Apply>
				</AppliesTo>
			</Stereotype>
			<Stereotype name="Architectural" notes="" cx="0" cy="0" bgcolor="-1" fontcolor="-1" bordercolor="-1" borderwidth="-1" hideicon="0" generalizes="RequirementBase" baseStereotypes="RequirementBase">
				<AppliesTo>
					<Apply type="Requirement"/>
				</AppliesTo>
			</Stereotype>
			<Stereotype name="AsciiDoc" notes="" cx="0" cy="0" bgcolor="-1" fontcolor="-1" bordercolor="-1" borderwidth="-1" hideicon="0" generalizes="PackageBase" baseStereotypes="PackageBase">
				<AppliesTo>
					<Apply type="Package">
						<Property name="URI" value=""/>
					</Apply>
				</AppliesTo>
				<TaggedValues>
					<Tag name="StartLevel" type="int" description="" unit="" values="" default=""/>
					<Tag name="ReqPrefix" type="char" description="" unit="" values="" default=""/>
					<Tag name="ComponentDefault" type="char" description="" unit="" values="" default=""/>
					<Tag name="ImageDirectory" type="char" description="" unit="" values="" default=""/>
					<Tag name="DefaultType" type="string" description="" unit="" values="" default=""/>
				</TaggedValues>
			</Stereotype>
			<Stereotype name="C" notes="" cx="0" cy="0" bgcolor="-1" fontcolor="-1" bordercolor="-1" borderwidth="-1" hideicon="0" generalizes="ClassBased" baseStereotypes="ClassBased"/>
			<Stereotype name="ClassBased" notes="" cx="0" cy="0" bgcolor="-1" fontcolor="-1" bordercolor="-1" borderwidth="-1" hideicon="0">
				<AppliesTo>
					<Apply type="Class">
						<Property name="isActive" value=""/>
					</Apply>
				</AppliesTo>
				<TaggedValues>
					<Tag name="ExtraInclude" type="string" description="" unit="" values="" default=""/>
				</TaggedValues>
			</Stereotype>
			<Stereotype name="Cxx" notes="" cx="0" cy="0" bgcolor="-1" fontcolor="-1" bordercolor="-1" borderwidth="-1" hideicon="0" generalizes="ClassBased" baseStereotypes="ClassBased">
				<TaggedValues>
					<Tag name="Serialize" type="bool" description="" unit="" values="true,false" default=""/>
					<Tag name="ByteOrder" type="enumeration" description="" unit="" values="Network,Host" default="Network"/>
				</TaggedValues>
			</Stereotype>
			<Stereotype name="default" notes="" cx="0" cy="0" bgcolor="-1" fontcolor="-1" bordercolor="-1" borderwidth="-1" hideicon="0">
				<AppliesTo>
					<Apply type="Operation">
						<Property name="isOrdered" value=""/>
						<Property name="isQuery" value="false"/>
						<Property name="isUnique" value=""/>
						<Property name="lower" value=""/>
						<Property name="upper" value=""/>
					</Apply>
				</AppliesTo>
			</Stereotype>
			<Stereotype name="delete" notes="" cx="0" cy="0" bgcolor="-1" fontcolor="-1" bordercolor="-1" borderwidth="-1" hideicon="0">
				<AppliesTo>
					<Apply type="Operation">
						<Property name="isOrdered" value=""/>
						<Property name="isQuery" value="false"/>
						<Property name="isUnique" value=""/>
						<Property name="lower" value=""/>
						<Property name="upper" value=""/>
					</Apply>
				</AppliesTo>
			</Stereotype>
			<Stereotype name="Enumeration" notes="" cx="0" cy="0" bgcolor="-1" fontcolor="-1" bordercolor="-1" borderwidth="-1" hideicon="0" generalizes="ClassBased" baseStereotypes="ClassBased"/>
			<Stereotype name="Extern" notes="" cx="0" cy="0" bgcolor="-1" fontcolor="-1" bordercolor="-1" borderwidth="-1" hideicon="0" generalizes="ClassBased" baseStereotypes="ClassBased"/>
			<Stereotype name="Functional" notes="" cx="0" cy="0" bgcolor="-1" fontcolor="-1" bordercolor="-1" borderwidth="-1" hideicon="0" generalizes="RequirementBase" baseStereotypes="RequirementBase">
				<AppliesTo>
					<Apply type="Requirement"/>
				</AppliesTo>
			</Stereotype>
			<Stereotype name="Header" notes="" cx="0" cy="0" bgcolor="-1" fontcolor="-1" bordercolor="-1" borderwidth="-1" hideicon="0" generalizes="RequirementBase" baseStereotypes="RequirementBase">
				<AppliesTo>
					<Apply type="Requirement"/>
				</AppliesTo>
			</Stereotype>
			<Stereotype name="Information" notes="" cx="0" cy="0" bgcolor="-1" fontcolor="-1" bordercolor="-1" borderwidth="-1" hideicon="0" generalizes="RequirementBase" baseStereotypes="RequirementBase">
				<AppliesTo>
					<Apply type="Requirement"/>
				</AppliesTo>
			</Stereotype>
			<Stereotype name="inline" notes="" cx="0" cy="0" bgcolor="-1" fontcolor="-1" bordercolor="-1" borderwidth="-1" hideicon="0">
				<AppliesTo>
					<Apply type="Operation">
						<Property name="isOrdered" value=""/>
						<Property name="isQuery" value="false"/>
						<Property name="isUnique" value=""/>
						<Property name="lower" value=""/>
						<Property name="upper" value=""/>
					</Apply>
				</AppliesTo>
			</Stereotype>
			<Stereotype name="json" notes="" cx="0" cy="0" bgcolor="-1" fontcolor="-1" bordercolor="-1" borderwidth="-1" hideicon="0">
				<AppliesTo>
					<Apply type="Signal"/>
				</AppliesTo>
			</Stereotype>
			<Stereotype name="Library" notes="" cx="0" cy="0" bgcolor="-1" fontcolor="-1" bordercolor="-1" borderwidth="-1" hideicon="0" generalizes="PackageBase" baseStereotypes="PackageBase">
				<AppliesTo>
					<Apply type="Package">
						<Property name="URI" value=""/>
					</Apply>
				</AppliesTo>
			</Stereotype>
			<Stereotype name="Model" notes="" cx="0" cy="0" bgcolor="-1" fontcolor="-1" bordercolor="-1" borderwidth="-1" hideicon="0" generalizes="PackageBase" baseStereotypes="PackageBase">
				<AppliesTo>
					<Apply type="Package">
						<Property name="URI" value=""/>
					</Apply>
				</AppliesTo>
			</Stereotype>
			<Stereotype name="ModelItem" notes="" cx="0" cy="0" bgcolor="-1" fontcolor="-1" bordercolor="-1" borderwidth="-1" hideicon="0" generalizes="ClassBased" baseStereotypes="ClassBased"/>
			<Stereotype name="Module" notes="" cx="0" cy="0" bgcolor="-1" fontcolor="-1" bordercolor="-1" borderwidth="-1" hideicon="0" generalizes="PackageBase" baseStereotypes="PackageBase">
				<AppliesTo>
					<Apply type="Package">
						<Property name="URI" value=""/>
					</Apply>
				</AppliesTo>
			</Stereotype>
			<Stereotype name="NonFunctional" notes="" cx="0" cy="0" bgcolor="-1" fontcolor="-1" bordercolor="-1" borderwidth="-1" hideicon="0" generalizes="RequirementBase" baseStereotypes="RequirementBase">
				<AppliesTo>
					<Apply type="Requirement"/>
				</AppliesTo>
			</Stereotype>
			<Stereotype name="PackageBase" notes="" cx="0" cy="0" bgcolor="-1" fontcolor="-1" bordercolor="-1" borderwidth="-1" hideicon="0">
				<TaggedValues>
					<Tag name="Directory" type="string" description="" unit="" values="" default=""/>
					<Tag name="OutputName" type="string" description="" unit="" values="" default=""/>
					<Tag name="ExtraInclude" type="string" description="" unit="" values="" default=""/>
					<Tag name="OutputPath" type="string" description="" unit="" values="" default=""/>
					<Tag name="Namespace" type="string" description="" unit="" values="" default=""/>
				</TaggedValues>
			</Stereotype>
			<Stereotype name="protobuf" notes="" cx="0" cy="0" bgcolor="-1" fontcolor="-1" bordercolor="-1" borderwidth="-1" hideicon="0">
				<AppliesTo>
					<Apply type="Signal"/>
				</AppliesTo>
			</Stereotype>
			<Stereotype name="Qt" notes="" cx="0" cy="0" bgcolor="-1" fontcolor="-1" bordercolor="-1" borderwidth="-1" hideicon="0" generalizes="ClassBased" baseStereotypes="ClassBased"/>
			<Stereotype name="RaAS" notes="" cx="0" cy="0" bgcolor="-1" fontcolor="-1" bordercolor="-1" borderwidth="-1" hideicon="0" generalizes="PackageBase" baseStereotypes="PackageBase">
				<AppliesTo>
					<Apply type="Package">
						<Property name="URI" value=""/>
					</Apply>
				</AppliesTo>
			</Stereotype>
			<Stereotype name="Rationale" notes="" cx="0" cy="0" bgcolor="-1" fontcolor="-1" bordercolor="-1" borderwidth="-1" hideicon="0" generalizes="RequirementBase" baseStereotypes="RequirementBase">
				<AppliesTo>
					<Apply type="Requirement"/>
				</AppliesTo>
			</Stereotype>
			<Stereotype name="RequirementBase" notes="" cx="0" cy="0" bgcolor="-1" fontcolor="-1" bordercolor="-1" borderwidth="-1" hideicon="0">
				<TaggedValues>
					<Tag name="status" type="enumeration" description="" unit="" values="new,draft,inreview,accepted,obsolete,reopened" default="new"/>
					<Tag name="level" type="enumeration" description="" unit="" values="system,software,component,unspecified" default="unspecified"/>
					<Tag name="component" type="char" description="" unit="" values="" default=""/>
				</TaggedValues>
			</Stereotype>
			<Stereotype name="Struct" notes="" cx="0" cy="0" bgcolor="-1" fontcolor="-1" bordercolor="-1" borderwidth="-1" hideicon="0" generalizes="ClassBased" baseStereotypes="ClassBased"/>
			<Stereotype name="System" notes="" cx="0" cy="0" bgcolor="-1" fontcolor="-1" bordercolor="-1" borderwidth="-1" hideicon="0" generalizes="PackageBase" baseStereotypes="PackageBase">
				<AppliesTo>
					<Apply type="Package">
						<Property name="URI" value=""/>
					</Apply>
				</AppliesTo>
			</Stereotype>
			<Stereotype name="template" notes="" cx="0" cy="0" bgcolor="-1" fontcolor="-1" bordercolor="-1" borderwidth="-1" hideicon="0">
				<AppliesTo>
					<Apply type="Operation">
						<Property name="isOrdered" value=""/>
						<Property name="isQuery" value="false"/>
						<Property name="isUnique" value=""/>
						<Property name="lower" value=""/>
						<Property name="upper" value=""/>
					</Apply>
				</AppliesTo>
				<TaggedValues>
					<Tag name="parameter" type="char" description="" unit="" values="" default=""/>
				</TaggedValues>
			</Stereotype>
			<Stereotype name="tlv" notes="" cx="0" cy="0" bgcolor="-1" fontcolor="-1" bordercolor="-1" borderwidth="-1" hideicon="0">
				<AppliesTo>
					<Apply type="Signal"/>
				</AppliesTo>
			</Stereotype>
			<Stereotype name="Union" notes="" cx="0" cy="0" bgcolor="-1" fontcolor="-1" bordercolor="-1" borderwidth="-1" hideicon="0" generalizes="ClassBased" baseStereotypes="ClassBased"/>
			<Stereotype name="WxApp" notes="" cx="0" cy="0" bgcolor="-1" fontcolor="-1" bordercolor="-1" borderwidth="-1" hideicon="0" generalizes="PackageBase" baseStereotypes="PackageBase">
				<AppliesTo>
					<Apply type="Package">
						<Property name="URI" value=""/>
					</Apply>
				</AppliesTo>
			</Stereotype>
			<Stereotype name="WxForm" notes="" cx="0" cy="0" bgcolor="-1" fontcolor="-1" bordercolor="-1" borderwidth="-1" hideicon="0" generalizes="ClassBased" baseStereotypes="ClassBased"/>
		</Stereotypes>
		<TaggedValueTypes/>
		<ViewDefinitions/>
		<Metamodel/>
	</Content>
</UMLProfile>